landmark_extractor
