Metadata-Version: 1.1
Name: landmark-extractor
Version: 0.2.4.3
Summary: A regular expression based extraction tool for extracting structured text from strings.
Home-page: https://github.com/inferlink/landmark-extractor
Author: InferLink
Author-email: developers@inferlink.com
License: BSD-4-Clause
Download-URL: https://github.com/inferlink/landmark-extractor
Platform: UNKNOWN
